odoo8_addon_hr_timesheet_print_employee_timesheet-8.0.1.0.0.99.dev4-nspkg.pth
odoo_addons/hr_timesheet_print_employee_timesheet/README.rst
odoo_addons/hr_timesheet_print_employee_timesheet/__init__.py
odoo_addons/hr_timesheet_print_employee_timesheet/__openerp__.py
odoo_addons/hr_timesheet_print_employee_timesheet/i18n/hr_timesheet_print_employee_timesheet.pot
odoo_addons/hr_timesheet_print_employee_timesheet/i18n/nl.po
odoo_addons/hr_timesheet_print_employee_timesheet/model/__init__.py
odoo_addons/hr_timesheet_print_employee_timesheet/model/hr_analytic_timesheet.py
odoo_addons/hr_timesheet_print_employee_timesheet/model/report.py
odoo_addons/hr_timesheet_print_employee_timesheet/report/hr_analytical_timesheet_employees.xml
odoo_addons/hr_timesheet_print_employee_timesheet/static/description/icon.png
odoo_addons/hr_timesheet_print_employee_timesheet/tests/__init__.py
odoo_addons/hr_timesheet_print_employee_timesheet/tests/test_hr_timesheet_print_employee_timesheet.py
odoo_addons/hr_timesheet_print_employee_timesheet/wizard/__init__.py
odoo_addons/hr_timesheet_print_employee_timesheet/wizard/hr_analytical_timesheet_employees.py
odoo_addons/hr_timesheet_print_employee_timesheet/wizard/hr_analytical_timesheet_employees.xml
odoo8_addon_hr_timesheet_print_employee_timesheet-8.0.1.0.0.99.dev4.dist-info/METADATA
odoo8_addon_hr_timesheet_print_employee_timesheet-8.0.1.0.0.99.dev4.dist-info/WHEEL
odoo8_addon_hr_timesheet_print_employee_timesheet-8.0.1.0.0.99.dev4.dist-info/namespace_packages.txt
odoo8_addon_hr_timesheet_print_employee_timesheet-8.0.1.0.0.99.dev4.dist-info/top_level.txt
odoo8_addon_hr_timesheet_print_employee_timesheet-8.0.1.0.0.99.dev4.dist-info/RECORD
